mums.py
setup.py
mums.egg-info/PKG-INFO
mums.egg-info/SOURCES.txt
mums.egg-info/dependency_links.txt
mums.egg-info/entry_points.txt
mums.egg-info/requires.txt
mums.egg-info/top_level.txt