Metadata-Version: 1.1
Name: mums
Version: 0.2
Summary: Simple encrypted environment variables
Home-page: http://github.com/pterk/mums
Author: Peter van Kampen
Author-email: pterk@datatailors.com
License: BSD
Platform: UNKNOWN
Classifier: License :: OSI Approved :: BSD License
Classifier: Programming Language :: Python
Classifier: Programming Language :: Python :: 3
Classifier: Operating System :: POSIX
